DOCUMENTATION.html
SpaceFuncs.py
__init__.py
__version__.py
setup.cfg
setup.py
SpaceFuncs.egg-info/PKG-INFO
SpaceFuncs.egg-info/SOURCES.txt
SpaceFuncs.egg-info/dependency_links.txt
SpaceFuncs.egg-info/requires.txt
SpaceFuncs.egg-info/top_level.txt
SpaceFuncs.egg-info/zip-safe
examples/__init__.py
examples/centroid.py
examples/contains.py
examples/graphics.py
examples/lineProjPlane.py
examples/linesIntersection.py
examples/maxArea.py
examples/pointProjLine.py
examples/pointProjPlane.py
examples/polygon.py
examples/skewLines.py
examples/tetrahedron.py
examples/triangle.py
kernel/Plot.py
kernel/Polygon.py
kernel/Polyhedron.py
kernel/Polytope.py
kernel/Tetrahedron.py
kernel/Triangle.py
kernel/__init__.py
kernel/baseGeometryObject.py
kernel/baseObjects.py
kernel/misc.py