Metadata-Version: 1.2
Name: SpaceFuncs
Version: 0.5602
Summary: A python module for 2D, 3D, ND space objects modelling and optimization
Home-page: http://openopt.org
Maintainer: Dmitrey Kroshko
Maintainer-email: dmitrey@openopt.org
License: BSD
Platform: UNKNOWN
Classifier: Development Status :: 5 - Production/Stable
Classifier: Environment :: Console
Classifier: Intended Audience :: Science/Research
Classifier: License :: OSI Approved :: BSD License
Classifier: Topic :: Scientific/Engineering
